failure_detector.py
failure_detector-0.1.1.dist-info/LICENSE.md
failure_detector-0.1.1.dist-info/METADATA
failure_detector-0.1.1.dist-info/WHEEL
failure_detector-0.1.1.dist-info/RECORD
