Metadata-Version: 2.1
Name: failure-detector
Version: 0.1.1
Summary: A Pythonic implementation of the Phi-Accrual failure detector
License: MIT
Author: Lucas Wolf
Author-email: iamlucaswolf@gmail.com
Requires-Python: >=3.12,<4.0
Classifier: License :: OSI Approved :: MIT License
Classifier: Programming Language :: Python :: 3
Classifier: Programming Language :: Python :: 3.12
